beautifhy/__init__.py
beautifhy/beautify.hy
beautifhy/core.hy
beautifhy/highlight.hy
beautifhy/reader.py
beautifhy-1.2.2.dist-info/licenses/AUTHORS
beautifhy-1.2.2.dist-info/licenses/LICENSE
beautifhy-1.2.2.dist-info/METADATA
beautifhy-1.2.2.dist-info/WHEEL
beautifhy-1.2.2.dist-info/entry_points.txt
beautifhy-1.2.2.dist-info/top_level.txt
beautifhy-1.2.2.dist-info/RECORD
