Metadata-Version: 2.4
Name: beautifhy
Version: 1.2.2
Summary: A Hy pretty-printer / code formatter / beautifier.
Author-email: Ati Sharma <ati+beautifhy@agalmic.ltd>
License: MIT License
Project-URL: Repository, https://github.com/atisharma/beautifhy
Keywords: hy,hylang,utilities,automation,formatter
Classifier: License :: OSI Approved :: MIT License
Classifier: Programming Language :: Python :: 3
Classifier: Programming Language :: Python :: 3.13
Classifier: Programming Language :: Python :: 3.14
Classifier: Programming Language :: Lisp
Classifier: Programming Language :: Hy
Classifier: Environment :: Console
Classifier: Intended Audience :: Developers
Classifier: Operating System :: OS Independent
Classifier: Topic :: Software Development :: Quality Assurance
Classifier: Topic :: Software Development :: Libraries
Classifier: Topic :: Utilities
Requires-Python: >=3.13
License-File: LICENSE
License-File: AUTHORS
Requires-Dist: hy>=1.2.0
Requires-Dist: hyrule>=1.0.0
Requires-Dist: multimethod>=2.0
Requires-Dist: pygments
Requires-Dist: toolz
Dynamic: license-file
